mlx90641_mcp2221/__init__.py
mlx90641_mcp2221/cli.py
mlx90641_mcp2221/mcp2221.py
mlx90641_mcp2221/libs/aarch64/libhidapi-hidraw.so
mlx90641_mcp2221/libs/aarch64/libmlx90641_driver_mcp2221.so
mlx90641_mcp2221/libs/aarch64/libudev.so
mlx90641_mcp2221/libs/armv7l/libhidapi-hidraw.so
mlx90641_mcp2221/libs/armv7l/libmlx90641_driver_mcp2221.so
mlx90641_mcp2221/libs/armv7l/libudev.so
mlx90641_mcp2221/libs/windows/hidapi.dll
mlx90641_mcp2221/libs/windows/mlx90641_driver_mcp2221.dll
mlx90641_mcp2221/libs/x86_64/libmlx90641_driver_mcp2221.so
mlx90641_driver_mcp2221-1.2.0.dist-info/LICENSE
mlx90641_driver_mcp2221-1.2.0.dist-info/METADATA
mlx90641_driver_mcp2221-1.2.0.dist-info/NOTICE
mlx90641_driver_mcp2221-1.2.0.dist-info/WHEEL
mlx90641_driver_mcp2221-1.2.0.dist-info/entry_points.txt
mlx90641_driver_mcp2221-1.2.0.dist-info/top_level.txt
mlx90641_driver_mcp2221-1.2.0.dist-info/RECORD
